hvorfra/__init__.py
hvorfra/assignment.py
hvorfra/ast.py
hvorfra/highlevel.py
hvorfra/py.typed
hvorfra/scope.py
hvorfra/stack.py
hvorfra/types.py
hvorfra-0.1.0.dist-info/METADATA
hvorfra-0.1.0.dist-info/WHEEL
hvorfra-0.1.0.dist-info/licenses/LICENSE
hvorfra-0.1.0.dist-info/RECORD
