Metadata-Version: 2.4
Name: hvorfra
Version: 0.1.0
Summary: A python package for inspecting the caller.
Author-email: Jesper Nielsen <jespernielsen1982+hvorfra@gmail.com>
License-Expression: MIT
License-File: LICENSE
Classifier: Development Status :: 4 - Beta
Classifier: Intended Audience :: Developers
Classifier: Programming Language :: Python :: 3
Classifier: Programming Language :: Python :: 3.12
Classifier: Programming Language :: Python :: 3.13
Classifier: Typing :: Typed
Requires-Python: <4,>=3.12
